argslib.py
argslib-2.1.0.dist-info/METADATA
argslib-2.1.0.dist-info/WHEEL
argslib-2.1.0.dist-info/top_level.txt
argslib-2.1.0.dist-info/RECORD
