Metadata-Version: 2.1
Name: argslib
Version: 2.1.0
Summary: A minimalist argument-parsing library.
Home-page: https://github.com/dmulholl/argslib
Author: Darren Mulholland
License: Public Domain
Classifier: Programming Language :: Python :: 3
Classifier: Operating System :: OS Independent
Classifier: License :: Public Domain
